{
    "mapPoint": [
        [
            1,
            {
                "x": 71,
                "y": 37,
                "z": 2,
                "linkedPoint": [
                    37,
                    225
                ]
            }
        ],
        [
            2,
            {
                "x": 68,
                "y": 38,
                "z": 4,
                "linkedPoint": [
                    176,
                    244
                ]
            }
        ],
        [
            3,
            {
                "x": 67,
                "y": 40,
                "z": 4,
                "linkedPoint": [
                    122,
                    244
                ]
            }
        ],
        [
            4,
            {
                "x": 66,
                "y": 45,
                "z": 6,
                "linkedPoint": [
                    6,
                    106
                ]
            }
        ],
        [
            5,
            {
                "x": 67,
                "y": 43,
                "z": 5,
                "linkedPoint": [
                    6,
                    238
                ]
            }
        ],
        [
            6,
            {
                "x": 66,
                "y": 44,
                "z": 5,
                "linkedPoint": [
                    4,
                    5
                ]
            }
        ],
        [
            7,
            {
                "x": 64,
                "y": 48,
                "z": 8,
                "linkedPoint": [
                    8,
                    223
                ]
            }
        ],
        [
            8,
            {
                "x": 64,
                "y": 47,
                "z": 7,
                "linkedPoint": [
                    7,
                    106
                ]
            }
        ],
        [
            9,
            {
                "x": 62,
                "y": 49,
                "z": 8,
                "linkedPoint": [
                    69,
                    223
                ]
            }
        ],
        [
            10,
            {
                "x": 60,
                "y": 27,
                "z": 3,
                "linkedPoint": [
                    11,
                    184
                ]
            }
        ],
        [
            11,
            {
                "x": 59,
                "y": 26,
                "z": 4,
                "linkedPoint": [
                    10,
                    12
                ]
            }
        ],
        [
            12,
            {
                "x": 58,
                "y": 25,
                "z": 4,
                "linkedPoint": [
                    11,
                    13
                ]
            }
        ],
        [
            13,
            {
                "x": 57,
                "y": 25,
                "z": 4,
                "linkedPoint": [
                    12,
                    15
                ]
            }
        ],
        [
            14,
            {
                "x": 56,
                "y": 50,
                "z": 11,
                "linkedPoint": [
                    16,
                    248
                ]
            }
        ],
        [
            15,
            {
                "x": 56,
                "y": 25,
                "z": 4,
                "linkedPoint": [
                    13,
                    81
                ]
            }
        ],
        [
            16,
            {
                "x": 55,
                "y": 51,
                "z": 11,
                "linkedPoint": [
                    14,
                    17
                ]
            }
        ],
        [
            17,
            {
                "x": 54,
                "y": 52,
                "z": 11,
                "linkedPoint": [
                    16,
                    58
                ]
            }
        ],
        [
            18,
            {
                "x": 54,
                "y": 47,
                "z": 10,
                "linkedPoint": [
                    114,
                    154
                ]
            }
        ],
        [
            19,
            {
                "x": 54,
                "y": 24,
                "z": 4,
                "linkedPoint": [
                    20,
                    81
                ]
            }
        ],
        [
            20,
            {
                "x": 53,
                "y": 24,
                "z": 4,
                "linkedPoint": [
                    19,
                    23
                ]
            }
        ],
        [
            21,
            {
                "x": 52,
                "y": 54,
                "z": 11,
                "linkedPoint": [
                    39,
                    58
                ]
            }
        ],
        [
            22,
            {
                "x": 52,
                "y": 46,
                "z": 10,
                "linkedPoint": [
                    25,
                    154,
                    218
                ]
            }
        ],
        [
            23,
            {
                "x": 52,
                "y": 25,
                "z": 5,
                "linkedPoint": [
                    20,
                    26
                ]
            }
        ],
        [
            24,
            {
                "x": 51,
                "y": 54,
                "z": 9,
                "linkedPoint": [
                    28,
                    39
                ]
            }
        ],
        [
            25,
            {
                "x": 51,
                "y": 45,
                "z": 10,
                "linkedPoint": [
                    22,
                    31
                ]
            }
        ],
        [
            26,
            {
                "x": 51,
                "y": 25,
                "z": 5,
                "linkedPoint": [
                    23,
                    199
                ]
            }
        ],
        [
            27,
            {
                "x": 51,
                "y": 49,
                "z": 9,
                "linkedPoint": [
                    30,
                    168
                ]
            }
        ],
        [
            28,
            {
                "x": 50,
                "y": 53,
                "z": 8,
                "linkedPoint": [
                    24,
                    29
                ]
            }
        ],
        [
            29,
            {
                "x": 50,
                "y": 52,
                "z": 8,
                "linkedPoint": [
                    28,
                    51
                ]
            }
        ],
        [
            30,
            {
                "x": 50,
                "y": 50,
                "z": 9,
                "linkedPoint": [
                    27,
                    51
                ]
            }
        ],
        [
            31,
            {
                "x": 50,
                "y": 45,
                "z": 9,
                "linkedPoint": [
                    25,
                    125
                ]
            }
        ],
        [
            32,
            {
                "x": 48,
                "y": 44,
                "z": 9,
                "linkedPoint": [
                    125,
                    226
                ]
            }
        ],
        [
            33,
            {
                "x": 48,
                "y": 25,
                "z": 5,
                "linkedPoint": [
                    76,
                    197
                ]
            }
        ],
        [
            34,
            {
                "x": 46,
                "y": 44,
                "z": 8,
                "linkedPoint": [
                    132,
                    226
                ]
            }
        ],
        [
            35,
            {
                "x": 45,
                "y": 24,
                "z": 6,
                "linkedPoint": [
                    36,
                    185
                ]
            }
        ],
        [
            36,
            {
                "x": 44,
                "y": 24,
                "z": 6,
                "linkedPoint": [
                    35,
                    38
                ]
            }
        ],
        [
            37,
            {
                "x": 70,
                "y": 37,
                "z": 3,
                "linkedPoint": [
                    1,
                    176
                ]
            }
        ],
        [
            38,
            {
                "x": 43,
                "y": 24,
                "z": 6,
                "linkedPoint": [
                    36,
                    112
                ]
            }
        ],
        [
            39,
            {
                "x": 51,
                "y": 54,
                "z": 10,
                "linkedPoint": [
                    21,
                    24
                ]
            }
        ],
        [
            40,
            {
                "x": 42,
                "y": 45,
                "z": 7,
                "linkedPoint": [
                    138,
                    139
                ]
            }
        ],
        [
            41,
            {
                "x": 40,
                "y": 44,
                "z": 6,
                "linkedPoint": [
                    98,
                    139
                ]
            }
        ],
        [
            42,
            {
                "x": 40,
                "y": 24,
                "z": 7,
                "linkedPoint": [
                    43,
                    78
                ]
            }
        ],
        [
            43,
            {
                "x": 39,
                "y": 24,
                "z": 7,
                "linkedPoint": [
                    42,
                    44,
                    189
                ]
            }
        ],
        [
            44,
            {
                "x": 38,
                "y": 25,
                "z": 7,
                "linkedPoint": [
                    43,
                    86,
                    189
                ]
            }
        ],
        [
            45,
            {
                "x": 38,
                "y": 44,
                "z": 6,
                "linkedPoint": [
                    98,
                    136
                ]
            }
        ],
        [
            46,
            {
                "x": 37,
                "y": 27,
                "z": 8,
                "linkedPoint": [
                    52,
                    86
                ]
            }
        ],
        [
            47,
            {
                "x": 37,
                "y": 23,
                "z": 7,
                "linkedPoint": [
                    48,
                    189
                ]
            }
        ],
        [
            48,
            {
                "x": 37,
                "y": 22,
                "z": 7,
                "linkedPoint": [
                    47,
                    163
                ]
            }
        ],
        [
            49,
            {
                "x": 36,
                "y": 43,
                "z": 6,
                "linkedPoint": [
                    53,
                    136
                ]
            }
        ],
        [
            50,
            {
                "x": 36,
                "y": 30,
                "z": 7,
                "linkedPoint": [
                    64,
                    212
                ]
            }
        ],
        [
            51,
            {
                "x": 50,
                "y": 51,
                "z": 9,
                "linkedPoint": [
                    29,
                    30
                ]
            }
        ],
        [
            52,
            {
                "x": 36,
                "y": 28,
                "z": 8,
                "linkedPoint": [
                    46,
                    212
                ]
            }
        ],
        [
            53,
            {
                "x": 35,
                "y": 42,
                "z": 6,
                "linkedPoint": [
                    49,
                    130
                ]
            }
        ],
        [
            54,
            {
                "x": 35,
                "y": 36,
                "z": 8,
                "linkedPoint": [
                    55,
                    63
                ]
            }
        ],
        [
            55,
            {
                "x": 35,
                "y": 35,
                "z": 7,
                "linkedPoint": [
                    54,
                    56
                ]
            }
        ],
        [
            56,
            {
                "x": 35,
                "y": 34,
                "z": 7,
                "linkedPoint": [
                    55,
                    57
                ]
            }
        ],
        [
            57,
            {
                "x": 35,
                "y": 33,
                "z": 8,
                "linkedPoint": [
                    56,
                    59
                ]
            }
        ],
        [
            58,
            {
                "x": 53,
                "y": 53,
                "z": 12,
                "linkedPoint": [
                    17,
                    21
                ]
            }
        ],
        [
            59,
            {
                "x": 35,
                "y": 32,
                "z": 8,
                "linkedPoint": [
                    57,
                    64
                ]
            }
        ],
        [
            60,
            {
                "x": 44,
                "y": 44,
                "z": 7,
                "linkedPoint": [
                    132,
                    138
                ]
            }
        ],
        [
            61,
            {
                "x": 35,
                "y": 19,
                "z": 7,
                "linkedPoint": [
                    65,
                    84
                ]
            }
        ],
        [
            62,
            {
                "x": 34,
                "y": 38,
                "z": 7,
                "linkedPoint": [
                    63,
                    71
                ]
            }
        ],
        [
            63,
            {
                "x": 34,
                "y": 37,
                "z": 7,
                "linkedPoint": [
                    54,
                    62
                ]
            }
        ],
        [
            64,
            {
                "x": 36,
                "y": 31,
                "z": 7,
                "linkedPoint": [
                    50,
                    59
                ]
            }
        ],
        [
            65,
            {
                "x": 34,
                "y": 18,
                "z": 6,
                "linkedPoint": [
                    61,
                    67
                ]
            }
        ],
        [
            66,
            {
                "x": 64,
                "y": 31,
                "z": 3,
                "linkedPoint": [
                    183,
                    187
                ]
            }
        ],
        [
            67,
            {
                "x": 34,
                "y": 17,
                "z": 6,
                "linkedPoint": [
                    65,
                    68
                ]
            }
        ],
        [
            68,
            {
                "x": 34,
                "y": 16,
                "z": 6,
                "linkedPoint": [
                    67,
                    206
                ]
            }
        ],
        [
            69,
            {
                "x": 61,
                "y": 50,
                "z": 9,
                "linkedPoint": [
                    9,
                    75
                ]
            }
        ],
        [
            70,
            {
                "x": 33,
                "y": 42,
                "z": 7,
                "linkedPoint": [
                    130,
                    141,
                    247
                ]
            }
        ],
        [
            71,
            {
                "x": 33,
                "y": 39,
                "z": 7,
                "linkedPoint": [
                    62,
                    193
                ]
            }
        ],
        [
            72,
            {
                "x": 33,
                "y": 14,
                "z": 6,
                "linkedPoint": [
                    73,
                    206
                ]
            }
        ],
        [
            73,
            {
                "x": 33,
                "y": 13,
                "z": 6,
                "linkedPoint": [
                    72,
                    74
                ]
            }
        ],
        [
            74,
            {
                "x": 33,
                "y": 12,
                "z": 6,
                "linkedPoint": [
                    73,
                    77
                ]
            }
        ],
        [
            75,
            {
                "x": 60,
                "y": 49,
                "z": 9,
                "linkedPoint": [
                    69,
                    111
                ]
            }
        ],
        [
            76,
            {
                "x": 49,
                "y": 25,
                "z": 5,
                "linkedPoint": [
                    33,
                    199
                ]
            }
        ],
        [
            77,
            {
                "x": 33,
                "y": 11,
                "z": 6,
                "linkedPoint": [
                    74,
                    79
                ]
            }
        ],
        [
            78,
            {
                "x": 41,
                "y": 24,
                "z": 7,
                "linkedPoint": [
                    42,
                    112
                ]
            }
        ],
        [
            79,
            {
                "x": 33,
                "y": 10,
                "z": 6,
                "linkedPoint": [
                    77,
                    80
                ]
            }
        ],
        [
            80,
            {
                "x": 33,
                "y": 9,
                "z": 5,
                "linkedPoint": [
                    79,
                    201
                ]
            }
        ],
        [
            81,
            {
                "x": 55,
                "y": 24,
                "z": 4,
                "linkedPoint": [
                    15,
                    19
                ]
            }
        ],
        [
            82,
            {
                "x": 33,
                "y": 7,
                "z": 6,
                "linkedPoint": [
                    83,
                    201
                ]
            }
        ],
        [
            83,
            {
                "x": 33,
                "y": 6,
                "z": 6,
                "linkedPoint": [
                    82,
                    252
                ]
            }
        ],
        [
            84,
            {
                "x": 36,
                "y": 20,
                "z": 6,
                "linkedPoint": [
                    61,
                    163
                ]
            }
        ],
        [
            85,
            {
                "x": 20,
                "y": 46,
                "z": 8,
                "linkedPoint": [
                    180,
                    219
                ]
            }
        ],
        [
            86,
            {
                "x": 38,
                "y": 26,
                "z": 7,
                "linkedPoint": [
                    44,
                    46
                ]
            }
        ],
        [
            87,
            {
                "x": 19,
                "y": 94,
                "z": 11,
                "linkedPoint": [
                    96,
                    159
                ]
            }
        ],
        [
            88,
            {
                "x": 29,
                "y": 52,
                "z": 6,
                "linkedPoint": [
                    234,
                    236
                ]
            }
        ],
        [
            89,
            {
                "x": 23,
                "y": 43,
                "z": 7,
                "linkedPoint": [
                    113,
                    208
                ]
            }
        ],
        [
            90,
            {
                "x": 19,
                "y": 91,
                "z": 11,
                "linkedPoint": [
                    129,
                    207
                ]
            }
        ],
        [
            91,
            {
                "x": 24,
                "y": 75,
                "z": 8,
                "linkedPoint": [
                    172,
                    204
                ]
            }
        ],
        [
            92,
            {
                "x": 19,
                "y": 88,
                "z": 11,
                "linkedPoint": [
                    147,
                    167
                ]
            }
        ],
        [
            93,
            {
                "x": 10,
                "y": 53,
                "z": 10,
                "linkedPoint": [
                    140,
                    203
                ]
            }
        ],
        [
            94,
            {
                "x": 19,
                "y": 78,
                "z": 11,
                "linkedPoint": [
                    133,
                    170,
                    175
                ]
            }
        ],
        [
            95,
            {
                "x": 65,
                "y": 33,
                "z": 3,
                "linkedPoint": [
                    135,
                    187
                ]
            }
        ],
        [
            96,
            {
                "x": 18,
                "y": 95,
                "z": 12,
                "linkedPoint": [
                    87,
                    152
                ]
            }
        ],
        [
            97,
            {
                "x": 18,
                "y": 50,
                "z": 10,
                "linkedPoint": [
                    108,
                    181
                ]
            }
        ],
        [
            98,
            {
                "x": 39,
                "y": 44,
                "z": 6,
                "linkedPoint": [
                    41,
                    45
                ]
            }
        ],
        [
            99,
            {
                "x": 17,
                "y": 76,
                "z": 10,
                "linkedPoint": [
                    101,
                    170
                ]
            }
        ],
        [
            100,
            {
                "x": 30,
                "y": 48,
                "z": 6,
                "linkedPoint": [
                    240,
                    243
                ]
            }
        ],
        [
            101,
            {
                "x": 17,
                "y": 75,
                "z": 10,
                "linkedPoint": [
                    99,
                    110
                ]
            }
        ],
        [
            102,
            {
                "x": 68,
                "y": 36,
                "z": 3,
                "linkedPoint": [
                    173,
                    176
                ]
            }
        ],
        [
            103,
            {
                "x": 14,
                "y": 61,
                "z": 10,
                "linkedPoint": [
                    174,
                    239
                ]
            }
        ],
        [
            104,
            {
                "x": 21,
                "y": 59,
                "z": 8,
                "linkedPoint": [
                    182,
                    250
                ]
            }
        ],
        [
            105,
            {
                "x": 17,
                "y": 58,
                "z": 10,
                "linkedPoint": [
                    128,
                    161
                ]
            }
        ],
        [
            106,
            {
                "x": 65,
                "y": 46,
                "z": 6,
                "linkedPoint": [
                    4,
                    8
                ]
            }
        ],
        [
            107,
            {
                "x": 19,
                "y": 58,
                "z": 9,
                "linkedPoint": [
                    161,
                    182
                ]
            }
        ],
        [
            108,
            {
                "x": 17,
                "y": 51,
                "z": 10,
                "linkedPoint": [
                    97,
                    115
                ]
            }
        ],
        [
            109,
            {
                "x": 22,
                "y": 77,
                "z": 9,
                "linkedPoint": [
                    202,
                    204
                ]
            }
        ],
        [
            110,
            {
                "x": 16,
                "y": 74,
                "z": 10,
                "linkedPoint": [
                    101,
                    116
                ]
            }
        ],
        [
            111,
            {
                "x": 59,
                "y": 49,
                "z": 9,
                "linkedPoint": [
                    75,
                    145
                ]
            }
        ],
        [
            112,
            {
                "x": 42,
                "y": 24,
                "z": 6,
                "linkedPoint": [
                    38,
                    78
                ]
            }
        ],
        [
            113,
            {
                "x": 22,
                "y": 44,
                "z": 7,
                "linkedPoint": [
                    89,
                    219
                ]
            }
        ],
        [
            114,
            {
                "x": 55,
                "y": 47,
                "z": 10,
                "linkedPoint": [
                    18,
                    217
                ]
            }
        ],
        [
            115,
            {
                "x": 16,
                "y": 52,
                "z": 10,
                "linkedPoint": [
                    108,
                    123
                ]
            }
        ],
        [
            116,
            {
                "x": 15,
                "y": 73,
                "z": 10,
                "linkedPoint": [
                    110,
                    119
                ]
            }
        ],
        [
            117,
            {
                "x": 23,
                "y": 59,
                "z": 7,
                "linkedPoint": [
                    209,
                    250
                ]
            }
        ],
        [
            118,
            {
                "x": 3,
                "y": 51,
                "z": 9,
                "linkedPoint": [
                    142,
                    178
                ]
            }
        ],
        [
            119,
            {
                "x": 15,
                "y": 72,
                "z": 10,
                "linkedPoint": [
                    116,
                    228
                ]
            }
        ],
        [
            120,
            {
                "x": 27,
                "y": 61,
                "z": 6,
                "linkedPoint": [
                    224,
                    242
                ]
            }
        ],
        [
            121,
            {
                "x": 15,
                "y": 58,
                "z": 10,
                "linkedPoint": [
                    124,
                    128,
                    148
                ]
            }
        ],
        [
            122,
            {
                "x": 67,
                "y": 41,
                "z": 5,
                "linkedPoint": [
                    3,
                    238
                ]
            }
        ],
        [
            123,
            {
                "x": 15,
                "y": 53,
                "z": 10,
                "linkedPoint": [
                    115,
                    213
                ]
            }
        ],
        [
            124,
            {
                "x": 14,
                "y": 59,
                "z": 10,
                "linkedPoint": [
                    121,
                    174
                ]
            }
        ],
        [
            125,
            {
                "x": 49,
                "y": 44,
                "z": 9,
                "linkedPoint": [
                    31,
                    32
                ]
            }
        ],
        [
            126,
            {
                "x": 14,
                "y": 56,
                "z": 10,
                "linkedPoint": [
                    148,
                    149
                ]
            }
        ],
        [
            127,
            {
                "x": 27,
                "y": 63,
                "z": 6,
                "linkedPoint": [
                    227,
                    242
                ]
            }
        ],
        [
            128,
            {
                "x": 16,
                "y": 58,
                "z": 10,
                "linkedPoint": [
                    105,
                    121
                ]
            }
        ],
        [
            129,
            {
                "x": 19,
                "y": 90,
                "z": 11,
                "linkedPoint": [
                    90,
                    147
                ]
            }
        ],
        [
            130,
            {
                "x": 34,
                "y": 42,
                "z": 6,
                "linkedPoint": [
                    53,
                    70
                ]
            }
        ],
        [
            131,
            {
                "x": 14,
                "y": 64,
                "z": 10,
                "linkedPoint": [
                    134,
                    160
                ]
            }
        ],
        [
            132,
            {
                "x": 45,
                "y": 44,
                "z": 8,
                "linkedPoint": [
                    34,
                    60
                ]
            }
        ],
        [
            133,
            {
                "x": 20,
                "y": 79,
                "z": 11,
                "linkedPoint": [
                    94,
                    175,
                    188
                ]
            }
        ],
        [
            134,
            {
                "x": 14,
                "y": 63,
                "z": 9,
                "linkedPoint": [
                    131,
                    239
                ]
            }
        ],
        [
            135,
            {
                "x": 66,
                "y": 34,
                "z": 4,
                "linkedPoint": [
                    95,
                    173
                ]
            }
        ],
        [
            136,
            {
                "x": 37,
                "y": 43,
                "z": 6,
                "linkedPoint": [
                    45,
                    49
                ]
            }
        ],
        [
            137,
            {
                "x": 13,
                "y": 54,
                "z": 10,
                "linkedPoint": [
                    149,
                    169,
                    213
                ]
            }
        ],
        [
            138,
            {
                "x": 43,
                "y": 44,
                "z": 7,
                "linkedPoint": [
                    40,
                    60
                ]
            }
        ],
        [
            139,
            {
                "x": 41,
                "y": 44,
                "z": 6,
                "linkedPoint": [
                    40,
                    41
                ]
            }
        ],
        [
            140,
            {
                "x": 9,
                "y": 52,
                "z": 9,
                "linkedPoint": [
                    93,
                    157
                ]
            }
        ],
        [
            141,
            {
                "x": 32,
                "y": 42,
                "z": 7,
                "linkedPoint": [
                    70,
                    241,
                    247
                ]
            }
        ],
        [
            142,
            {
                "x": 2,
                "y": 51,
                "z": 9,
                "linkedPoint": [
                    118
                ]
            }
        ],
        [
            143,
            {
                "x": 7,
                "y": 52,
                "z": 9,
                "linkedPoint": [
                    157,
                    164
                ]
            }
        ],
        [
            144,
            {
                "x": 25,
                "y": 59,
                "z": 6,
                "linkedPoint": [
                    209,
                    235
                ]
            }
        ],
        [
            145,
            {
                "x": 58,
                "y": 49,
                "z": 10,
                "linkedPoint": [
                    111,
                    248
                ]
            }
        ],
        [
            146,
            {
                "x": 27,
                "y": 68,
                "z": 6,
                "linkedPoint": [
                    158,
                    220
                ]
            }
        ],
        [
            147,
            {
                "x": 19,
                "y": 89,
                "z": 11,
                "linkedPoint": [
                    92,
                    129
                ]
            }
        ],
        [
            148,
            {
                "x": 14,
                "y": 57,
                "z": 10,
                "linkedPoint": [
                    121,
                    126
                ]
            }
        ],
        [
            149,
            {
                "x": 14,
                "y": 55,
                "z": 10,
                "linkedPoint": [
                    126,
                    137,
                    213
                ]
            }
        ],
        [
            150,
            {
                "x": 19,
                "y": 48,
                "z": 8,
                "linkedPoint": [
                    180,
                    181
                ]
            }
        ],
        [
            151,
            {
                "x": 27,
                "y": 66,
                "z": 6,
                "linkedPoint": [
                    220,
                    229
                ]
            }
        ],
        [
            152,
            {
                "x": 19,
                "y": 96,
                "z": 12,
                "linkedPoint": [
                    96,
                    162
                ]
            }
        ],
        [
            153,
            {
                "x": 14,
                "y": 66,
                "z": 9,
                "linkedPoint": [
                    160,
                    166
                ]
            }
        ],
        [
            154,
            {
                "x": 53,
                "y": 46,
                "z": 10,
                "linkedPoint": [
                    18,
                    22,
                    218
                ]
            }
        ],
        [
            155,
            {
                "x": 14,
                "y": 68,
                "z": 10,
                "linkedPoint": [
                    165,
                    166
                ]
            }
        ],
        [
            156,
            {
                "x": 33,
                "y": 4,
                "z": 6,
                "linkedPoint": [
                    251,
                    252
                ]
            }
        ],
        [
            157,
            {
                "x": 8,
                "y": 52,
                "z": 9,
                "linkedPoint": [
                    140,
                    143
                ]
            }
        ],
        [
            158,
            {
                "x": 27,
                "y": 69,
                "z": 6,
                "linkedPoint": [
                    146,
                    214
                ]
            }
        ],
        [
            159,
            {
                "x": 19,
                "y": 93,
                "z": 11,
                "linkedPoint": [
                    87,
                    207
                ]
            }
        ],
        [
            160,
            {
                "x": 14,
                "y": 65,
                "z": 10,
                "linkedPoint": [
                    131,
                    153
                ]
            }
        ],
        [
            161,
            {
                "x": 18,
                "y": 58,
                "z": 10,
                "linkedPoint": [
                    105,
                    107
                ]
            }
        ],
        [
            162,
            {
                "x": 19,
                "y": 97,
                "z": 11,
                "linkedPoint": [
                    152
                ]
            }
        ],
        [
            163,
            {
                "x": 36,
                "y": 21,
                "z": 7,
                "linkedPoint": [
                    48,
                    84
                ]
            }
        ],
        [
            164,
            {
                "x": 6,
                "y": 52,
                "z": 9,
                "linkedPoint": [
                    143,
                    233
                ]
            }
        ],
        [
            165,
            {
                "x": 14,
                "y": 69,
                "z": 10,
                "linkedPoint": [
                    155,
                    179
                ]
            }
        ],
        [
            166,
            {
                "x": 14,
                "y": 67,
                "z": 10,
                "linkedPoint": [
                    153,
                    155
                ]
            }
        ],
        [
            167,
            {
                "x": 19,
                "y": 87,
                "z": 10,
                "linkedPoint": [
                    92,
                    192
                ]
            }
        ],
        [
            168,
            {
                "x": 52,
                "y": 48,
                "z": 9,
                "linkedPoint": [
                    27,
                    218
                ]
            }
        ],
        [
            169,
            {
                "x": 12,
                "y": 53,
                "z": 10,
                "linkedPoint": [
                    137,
                    203
                ]
            }
        ],
        [
            170,
            {
                "x": 18,
                "y": 77,
                "z": 10,
                "linkedPoint": [
                    94,
                    99
                ]
            }
        ],
        [
            171,
            {
                "x": 27,
                "y": 58,
                "z": 6,
                "linkedPoint": [
                    231,
                    235
                ]
            }
        ],
        [
            172,
            {
                "x": 24,
                "y": 74,
                "z": 8,
                "linkedPoint": [
                    91,
                    211
                ]
            }
        ],
        [
            173,
            {
                "x": 67,
                "y": 35,
                "z": 4,
                "linkedPoint": [
                    102,
                    135
                ]
            }
        ],
        [
            174,
            {
                "x": 14,
                "y": 60,
                "z": 10,
                "linkedPoint": [
                    103,
                    124
                ]
            }
        ],
        [
            175,
            {
                "x": 20,
                "y": 78,
                "z": 10,
                "linkedPoint": [
                    94,
                    133,
                    202
                ]
            }
        ],
        [
            176,
            {
                "x": 69,
                "y": 37,
                "z": 3,
                "linkedPoint": [
                    2,
                    37,
                    102
                ]
            }
        ],
        [
            177,
            {
                "x": 62,
                "y": 29,
                "z": 3,
                "linkedPoint": [
                    183,
                    184
                ]
            }
        ],
        [
            178,
            {
                "x": 4,
                "y": 51,
                "z": 9,
                "linkedPoint": [
                    118,
                    233
                ]
            }
        ],
        [
            179,
            {
                "x": 14,
                "y": 70,
                "z": 10,
                "linkedPoint": [
                    165,
                    228
                ]
            }
        ],
        [
            180,
            {
                "x": 20,
                "y": 47,
                "z": 8,
                "linkedPoint": [
                    85,
                    150
                ]
            }
        ],
        [
            181,
            {
                "x": 19,
                "y": 49,
                "z": 9,
                "linkedPoint": [
                    97,
                    150
                ]
            }
        ],
        [
            182,
            {
                "x": 20,
                "y": 58,
                "z": 9,
                "linkedPoint": [
                    104,
                    107
                ]
            }
        ],
        [
            183,
            {
                "x": 63,
                "y": 30,
                "z": 3,
                "linkedPoint": [
                    66,
                    177
                ]
            }
        ],
        [
            184,
            {
                "x": 61,
                "y": 28,
                "z": 3,
                "linkedPoint": [
                    10,
                    177
                ]
            }
        ],
        [
            185,
            {
                "x": 46,
                "y": 24,
                "z": 6,
                "linkedPoint": [
                    35,
                    197
                ]
            }
        ],
        [
            186,
            {
                "x": 29,
                "y": 54,
                "z": 6,
                "linkedPoint": [
                    194,
                    236
                ]
            }
        ],
        [
            187,
            {
                "x": 65,
                "y": 32,
                "z": 3,
                "linkedPoint": [
                    66,
                    95
                ]
            }
        ],
        [
            188,
            {
                "x": 20,
                "y": 80,
                "z": 11,
                "linkedPoint": [
                    133,
                    191
                ]
            }
        ],
        [
            189,
            {
                "x": 38,
                "y": 24,
                "z": 7,
                "linkedPoint": [
                    43,
                    44,
                    47
                ]
            }
        ],
        [
            190,
            {
                "x": 28,
                "y": 41,
                "z": 6,
                "linkedPoint": [
                    205,
                    222
                ]
            }
        ],
        [
            191,
            {
                "x": 20,
                "y": 81,
                "z": 11,
                "linkedPoint": [
                    188,
                    246
                ]
            }
        ],
        [
            192,
            {
                "x": 20,
                "y": 86,
                "z": 10,
                "linkedPoint": [
                    167,
                    198
                ]
            }
        ],
        [
            193,
            {
                "x": 32,
                "y": 40,
                "z": 6,
                "linkedPoint": [
                    71,
                    241
                ]
            }
        ],
        [
            194,
            {
                "x": 28,
                "y": 55,
                "z": 6,
                "linkedPoint": [
                    186,
                    196
                ]
            }
        ],
        [
            195,
            {
                "x": 20,
                "y": 84,
                "z": 11,
                "linkedPoint": [
                    198,
                    215
                ]
            }
        ],
        [
            196,
            {
                "x": 28,
                "y": 56,
                "z": 6,
                "linkedPoint": [
                    194,
                    231
                ]
            }
        ],
        [
            197,
            {
                "x": 47,
                "y": 25,
                "z": 5,
                "linkedPoint": [
                    33,
                    185
                ]
            }
        ],
        [
            198,
            {
                "x": 20,
                "y": 85,
                "z": 11,
                "linkedPoint": [
                    192,
                    195
                ]
            }
        ],
        [
            199,
            {
                "x": 50,
                "y": 25,
                "z": 5,
                "linkedPoint": [
                    26,
                    76
                ]
            }
        ],
        [
            200,
            {
                "x": 31,
                "y": 46,
                "z": 6,
                "linkedPoint": [
                    240,
                    245
                ]
            }
        ],
        [
            201,
            {
                "x": 33,
                "y": 8,
                "z": 6,
                "linkedPoint": [
                    80,
                    82
                ]
            }
        ],
        [
            202,
            {
                "x": 21,
                "y": 78,
                "z": 9,
                "linkedPoint": [
                    109,
                    175
                ]
            }
        ],
        [
            203,
            {
                "x": 11,
                "y": 53,
                "z": 10,
                "linkedPoint": [
                    93,
                    169
                ]
            }
        ],
        [
            204,
            {
                "x": 23,
                "y": 76,
                "z": 9,
                "linkedPoint": [
                    91,
                    109
                ]
            }
        ],
        [
            205,
            {
                "x": 29,
                "y": 41,
                "z": 6,
                "linkedPoint": [
                    190,
                    237
                ]
            }
        ],
        [
            206,
            {
                "x": 34,
                "y": 15,
                "z": 6,
                "linkedPoint": [
                    68,
                    72
                ]
            }
        ],
        [
            207,
            {
                "x": 19,
                "y": 92,
                "z": 11,
                "linkedPoint": [
                    90,
                    159
                ]
            }
        ],
        [
            208,
            {
                "x": 24,
                "y": 42,
                "z": 7,
                "linkedPoint": [
                    89,
                    210
                ]
            }
        ],
        [
            209,
            {
                "x": 24,
                "y": 59,
                "z": 7,
                "linkedPoint": [
                    117,
                    144
                ]
            }
        ],
        [
            210,
            {
                "x": 25,
                "y": 41,
                "z": 6,
                "linkedPoint": [
                    208,
                    230
                ]
            }
        ],
        [
            211,
            {
                "x": 25,
                "y": 73,
                "z": 7,
                "linkedPoint": [
                    172,
                    221
                ]
            }
        ],
        [
            212,
            {
                "x": 36,
                "y": 29,
                "z": 8,
                "linkedPoint": [
                    50,
                    52
                ]
            }
        ],
        [
            213,
            {
                "x": 14,
                "y": 54,
                "z": 10,
                "linkedPoint": [
                    123,
                    137,
                    149
                ]
            }
        ],
        [
            214,
            {
                "x": 26,
                "y": 70,
                "z": 7,
                "linkedPoint": [
                    158,
                    216
                ]
            }
        ],
        [
            215,
            {
                "x": 20,
                "y": 83,
                "z": 11,
                "linkedPoint": [
                    195,
                    246
                ]
            }
        ],
        [
            216,
            {
                "x": 26,
                "y": 71,
                "z": 7,
                "linkedPoint": [
                    214,
                    221
                ]
            }
        ],
        [
            217,
            {
                "x": 56,
                "y": 48,
                "z": 10,
                "linkedPoint": [
                    114,
                    248
                ]
            }
        ],
        [
            218,
            {
                "x": 52,
                "y": 47,
                "z": 9,
                "linkedPoint": [
                    22,
                    154,
                    168
                ]
            }
        ],
        [
            219,
            {
                "x": 21,
                "y": 45,
                "z": 7,
                "linkedPoint": [
                    85,
                    113
                ]
            }
        ],
        [
            220,
            {
                "x": 27,
                "y": 67,
                "z": 7,
                "linkedPoint": [
                    146,
                    151
                ]
            }
        ],
        [
            221,
            {
                "x": 26,
                "y": 72,
                "z": 7,
                "linkedPoint": [
                    211,
                    216
                ]
            }
        ],
        [
            222,
            {
                "x": 27,
                "y": 40,
                "z": 6,
                "linkedPoint": [
                    190,
                    230
                ]
            }
        ],
        [
            223,
            {
                "x": 63,
                "y": 49,
                "z": 8,
                "linkedPoint": [
                    7,
                    9
                ]
            }
        ],
        [
            224,
            {
                "x": 27,
                "y": 60,
                "z": 6,
                "linkedPoint": [
                    120,
                    235
                ]
            }
        ],
        [
            225,
            {
                "x": 72,
                "y": 37,
                "z": 2,
                "linkedPoint": [
                    1
                ]
            }
        ],
        [
            226,
            {
                "x": 47,
                "y": 44,
                "z": 8,
                "linkedPoint": [
                    32,
                    34
                ]
            }
        ],
        [
            227,
            {
                "x": 27,
                "y": 64,
                "z": 6,
                "linkedPoint": [
                    127,
                    229
                ]
            }
        ],
        [
            228,
            {
                "x": 14,
                "y": 71,
                "z": 9,
                "linkedPoint": [
                    119,
                    179
                ]
            }
        ],
        [
            229,
            {
                "x": 27,
                "y": 65,
                "z": 6,
                "linkedPoint": [
                    151,
                    227
                ]
            }
        ],
        [
            230,
            {
                "x": 26,
                "y": 41,
                "z": 6,
                "linkedPoint": [
                    210,
                    222
                ]
            }
        ],
        [
            231,
            {
                "x": 28,
                "y": 57,
                "z": 6,
                "linkedPoint": [
                    171,
                    196
                ]
            }
        ],
        [
            232,
            {
                "x": 29,
                "y": 50,
                "z": 7,
                "linkedPoint": [
                    234,
                    243
                ]
            }
        ],
        [
            233,
            {
                "x": 5,
                "y": 51,
                "z": 9,
                "linkedPoint": [
                    164,
                    178
                ]
            }
        ],
        [
            234,
            {
                "x": 29,
                "y": 51,
                "z": 7,
                "linkedPoint": [
                    88,
                    232
                ]
            }
        ],
        [
            235,
            {
                "x": 26,
                "y": 59,
                "z": 6,
                "linkedPoint": [
                    144,
                    171,
                    224
                ]
            }
        ],
        [
            236,
            {
                "x": 29,
                "y": 53,
                "z": 6,
                "linkedPoint": [
                    88,
                    186
                ]
            }
        ],
        [
            237,
            {
                "x": 30,
                "y": 41,
                "z": 7,
                "linkedPoint": [
                    205,
                    241
                ]
            }
        ],
        [
            238,
            {
                "x": 67,
                "y": 42,
                "z": 5,
                "linkedPoint": [
                    5,
                    122
                ]
            }
        ],
        [
            239,
            {
                "x": 14,
                "y": 62,
                "z": 9,
                "linkedPoint": [
                    103,
                    134
                ]
            }
        ],
        [
            240,
            {
                "x": 30,
                "y": 47,
                "z": 6,
                "linkedPoint": [
                    100,
                    200
                ]
            }
        ],
        [
            241,
            {
                "x": 31,
                "y": 41,
                "z": 6,
                "linkedPoint": [
                    141,
                    193,
                    237
                ]
            }
        ],
        [
            242,
            {
                "x": 27,
                "y": 62,
                "z": 6,
                "linkedPoint": [
                    120,
                    127
                ]
            }
        ],
        [
            243,
            {
                "x": 30,
                "y": 49,
                "z": 6,
                "linkedPoint": [
                    100,
                    232
                ]
            }
        ],
        [
            244,
            {
                "x": 68,
                "y": 39,
                "z": 4,
                "linkedPoint": [
                    2,
                    3
                ]
            }
        ],
        [
            245,
            {
                "x": 31,
                "y": 45,
                "z": 6,
                "linkedPoint": [
                    200,
                    249
                ]
            }
        ],
        [
            246,
            {
                "x": 20,
                "y": 82,
                "z": 11,
                "linkedPoint": [
                    191,
                    215
                ]
            }
        ],
        [
            247,
            {
                "x": 32,
                "y": 43,
                "z": 6,
                "linkedPoint": [
                    70,
                    141,
                    249
                ]
            }
        ],
        [
            248,
            {
                "x": 57,
                "y": 49,
                "z": 10,
                "linkedPoint": [
                    14,
                    145,
                    217
                ]
            }
        ],
        [
            249,
            {
                "x": 32,
                "y": 44,
                "z": 6,
                "linkedPoint": [
                    245,
                    247
                ]
            }
        ],
        [
            250,
            {
                "x": 22,
                "y": 59,
                "z": 7,
                "linkedPoint": [
                    104,
                    117
                ]
            }
        ],
        [
            251,
            {
                "x": 33,
                "y": 3,
                "z": 6,
                "linkedPoint": [
                    156
                ]
            }
        ],
        [
            252,
            {
                "x": 33,
                "y": 5,
                "z": 6,
                "linkedPoint": [
                    83,
                    156
                ]
            }
        ]
    ]
}